django_adminform/__init__.py
django_adminform/admin.py
django_adminform/apps.py
django_adminform/tests.py
django_adminform/urls.py
django_adminform/views.py
django_adminform/widgets.py
django_adminform/forms/__init__.py
django_adminform/forms/compat.py
django_adminform/forms/fields.py
django_adminform/models/__init__.py
django_adminform/models/compat.py
django_adminform/models/fields.py
django_adminform/static/django_adminform/react-json-form.min.js
django_adminform/static/django_adminform/react-json-form.min.js.map
django_adminform/static/django_adminform/style.css
django_adminform/static/django_adminform/img/arrow-icons.svg
django_adminform/static/django_adminform/img/control-icons.svg
django_adminform/static/django_adminform/img/icon-addlink.svg
django_adminform/static/django_adminform/img/icon-changelink.svg
django_adminform/static/django_adminform/img/icon-deletelink.svg
django_adminform/static/django_adminform/vendor/react-dom.production.min.js
django_adminform/static/django_adminform/vendor/react.production.min.js
django_adminform/templates/django_adminform/editor.html
django_adminform-1.0.5.dist-info/LICENSE.txt
django_adminform-1.0.5.dist-info/METADATA
django_adminform-1.0.5.dist-info/WHEEL
django_adminform-1.0.5.dist-info/top_level.txt
django_adminform-1.0.5.dist-info/RECORD
